gvm/__init__.py
gvm/__version__.py
gvm/_enum.py
gvm/connections/__init__.py
gvm/connections/_connection.py
gvm/connections/_debug.py
gvm/connections/_ssh.py
gvm/connections/_tls.py
gvm/connections/_unix.py
gvm/errors.py
gvm/protocols/__init__.py
gvm/protocols/_protocol.py
gvm/protocols/core/__init__.py
gvm/protocols/core/_connection.py
gvm/protocols/core/_request.py
gvm/protocols/core/_response.py
gvm/protocols/gmp/__init__.py
gvm/protocols/gmp/_gmp.py
gvm/protocols/gmp/_gmp224.py
gvm/protocols/gmp/_gmp225.py
gvm/protocols/gmp/_gmp226.py
gvm/protocols/gmp/_gmp227.py
gvm/protocols/gmp/_gmpnext.py
gvm/protocols/gmp/requests/__init__.py
gvm/protocols/gmp/requests/_entity_id.py
gvm/protocols/gmp/requests/_version.py
gvm/protocols/gmp/requests/next/__init__.py
gvm/protocols/gmp/requests/next/_agent_groups.py
gvm/protocols/gmp/requests/next/_agent_installers.py
gvm/protocols/gmp/requests/next/_agents.py
gvm/protocols/gmp/requests/next/_credential_stores.py
gvm/protocols/gmp/requests/next/_credentials.py
gvm/protocols/gmp/requests/next/_oci_image_targets.py
gvm/protocols/gmp/requests/next/_tasks.py
gvm/protocols/gmp/requests/v224/__init__.py
gvm/protocols/gmp/requests/v224/_aggregates.py
gvm/protocols/gmp/requests/v224/_alerts.py
gvm/protocols/gmp/requests/v224/_audits.py
gvm/protocols/gmp/requests/v224/_auth.py
gvm/protocols/gmp/requests/v224/_cert_bund_advisories.py
gvm/protocols/gmp/requests/v224/_cpes.py
gvm/protocols/gmp/requests/v224/_credentials.py
gvm/protocols/gmp/requests/v224/_cves.py
gvm/protocols/gmp/requests/v224/_dfn_cert_advisories.py
gvm/protocols/gmp/requests/v224/_entity_type.py
gvm/protocols/gmp/requests/v224/_feed.py
gvm/protocols/gmp/requests/v224/_filters.py
gvm/protocols/gmp/requests/v224/_groups.py
gvm/protocols/gmp/requests/v224/_help.py
gvm/protocols/gmp/requests/v224/_hosts.py
gvm/protocols/gmp/requests/v224/_notes.py
gvm/protocols/gmp/requests/v224/_nvts.py
gvm/protocols/gmp/requests/v224/_operating_systems.py
python_gvm-26.9.0.dist-info/METADATA
python_gvm-26.9.0.dist-info/WHEEL
python_gvm-26.9.0.dist-info/licenses/LICENSE
python_gvm-26.9.0.dist-info/RECORD
