Metadata-Version: 2.4
Name: python-gvm
Version: 26.9.0
Summary: Library to communicate with remote servers over GMP or OSP
License: GPL-3.0-or-later
License-File: LICENSE
Author: Greenbone AG
Author-email: info@greenbone.net
Requires-Python: >=3.9.2,<4.0.0
Classifier: Development Status :: 5 - Production/Stable
Classifier: Environment :: Console
Classifier: Intended Audience :: Developers
Classifier: License :: OSI Approved :: GNU General Public License v3 or later (GPLv3+)
Classifier: Operating System :: OS Independent
Classifier: Programming Language :: Python :: 3
Classifier: Programming Language :: Python :: 3.10
Classifier: Programming Language :: Python :: 3.11
Classifier: Programming Language :: Python :: 3.12
Classifier: Programming Language :: Python :: 3.13
Classifier: Programming Language :: Python :: 3.14
Classifier: Programming Language :: Python :: 3.9
Classifier: Topic :: Software Development :: Libraries :: Python Modules
Requires-Dist: httpx[http2] (>=0.28.1,<0.29.0)
Requires-Dist: lxml (>=4.5.0)
Requires-Dist: paramiko (>=2.7.1)
Project-URL: Documentation, https://greenbone.github.io/python-gvm/
Project-URL: Homepage, https://github.com/greenbone/python-gvm/
Project-URL: Repository, https://github.com/greenbone/python-gvm/
